odoo/addons/project_task_block_reason/README.rst
odoo/addons/project_task_block_reason/__init__.py
odoo/addons/project_task_block_reason/__manifest__.py
odoo/addons/project_task_block_reason/i18n/ca_ES.po
odoo/addons/project_task_block_reason/i18n/es.po
odoo/addons/project_task_block_reason/models/__init__.py
odoo/addons/project_task_block_reason/models/task.py
odoo/addons/project_task_block_reason/readme/CONTRIBUTORS.rst
odoo/addons/project_task_block_reason/readme/DESCRIPTION.rst
odoo/addons/project_task_block_reason/readme/USAGE.rst
odoo/addons/project_task_block_reason/static/description/icon.png
odoo/addons/project_task_block_reason/static/description/index.html
odoo/addons/project_task_block_reason/static/img/example_form.png
odoo/addons/project_task_block_reason/static/img/example_kanban.png
odoo/addons/project_task_block_reason/tests/__init__.py
odoo/addons/project_task_block_reason/tests/test_project_task_block_reason.py
odoo/addons/project_task_block_reason/views/project_views.xml
odoo_addon_project_task_block_reason-16.0.1.0.0.dist-info/METADATA
odoo_addon_project_task_block_reason-16.0.1.0.0.dist-info/WHEEL
odoo_addon_project_task_block_reason-16.0.1.0.0.dist-info/top_level.txt
odoo_addon_project_task_block_reason-16.0.1.0.0.dist-info/RECORD
