Metadata-Version: 2.1
Name: odoo-addon-project_task_block_reason
Version: 16.0.1.0.0
Requires-Python: >=3.10
Requires-Dist: odoo>=16.0a,<16.1dev
Summary: Introduce a reason when a task is blocked
Home-page: https://github.com/sygel-technology/sy-project
License: AGPL-3
Author: Sygel
Classifier: Programming Language :: Python
Classifier: Framework :: Odoo
Classifier: Framework :: Odoo :: 16.0
Classifier: License :: OSI Approved :: GNU Affero General Public License v3
